check_mysql_slave/__init__.py
check_mysql_slave-0.2.3.dist-info/LICENSE.txt
check_mysql_slave-0.2.3.dist-info/METADATA
check_mysql_slave-0.2.3.dist-info/WHEEL
check_mysql_slave-0.2.3.dist-info/entry_points.txt
check_mysql_slave-0.2.3.dist-info/top_level.txt
check_mysql_slave-0.2.3.dist-info/RECORD
