Metadata-Version: 2.1
Name: check-mysql-slave
Version: 0.2.3
Summary: Check MySQL seconds behind master for Nagios-like monitoring.
Home-page: https://git.shore.co.il/nimrod/check_mysql_slave
Author: Nimrod Adar
Author-email: nimrod@shore.co.il
License: MIT
Keywords: nagios mysql slave replication monitoring
Platform: UNKNOWN
Classifier: Development Status :: 4 - Beta
Classifier: Intended Audience :: System Administrators
Classifier: Programming Language :: Python :: 3
Classifier: Programming Language :: Python :: 3.6
Classifier: Programming Language :: Python :: 3.7
Classifier: Programming Language :: Python :: 3.8
Classifier: Programming Language :: Python :: 3.9
Classifier: Programming Language :: Python :: 2
Classifier: Programming Language :: Python :: 2.7
Classifier: Topic :: Utilities
Classifier: License :: OSI Approved :: MIT License
Requires-Dist: mysqlclient
